ASSUMPTIONS.md
CHANGELOG.md
README.md
ROADMAP.md
data/ETH_1H.csv.zip
data/ETH_1min.csv.zip
data/ETH_day.csv
data/README.md
data/__init__.py
data/api/__init__.py
data/api/beaconchain.py
data/api/etherscan.py
data/daily_extracted_mev.json
data/ether_avg_gas_price.csv
data/ether_block_rewards.csv
data/ether_gas_used.csv
data/ether_price.csv
data/ether_supply.csv
data/historical_values.py
experiments/.gitkeep
experiments/__init__.py
experiments/default_experiment.py
experiments/notebooks/0_README.ipynb
experiments/notebooks/1_model_validation.ipynb
experiments/notebooks/2_validator_revenue_and_profit_yields.ipynb
experiments/notebooks/3_network_issuance_and_inflation_rate.ipynb
experiments/notebooks/Untitled.ipynb
experiments/notebooks/setup.py
experiments/notebooks/simulation_profiling/project_path.py
experiments/notebooks/simulation_profiling/simulation_timestep_substep_profiling.ipynb
experiments/notebooks/template.ipynb
experiments/notebooks/visualizations/__init__.py
experiments/notebooks/visualizations/assets/default_stylesheet.css
experiments/notebooks/visualizations/assets/style.css
experiments/notebooks/visualizations/eth_supply_simulator.py
experiments/notebooks/visualizations/plotly_theme.py
experiments/notebooks/walk-through.ipynb
experiments/outputs/hoban_borgers_economic_model/experiment_model_validation_scenario_1a.png
experiments/outputs/hoban_borgers_economic_model/experiment_model_validation_scenario_1b.png
experiments/outputs/hoban_borgers_economic_model/experiment_model_validation_scenario_2.png
experiments/outputs/hoban_borgers_economic_model/experiment_model_validation_scenario_3a.png
experiments/outputs/hoban_borgers_economic_model/experiment_model_validation_scenario_3b.png
experiments/outputs/validator_environment_yield_contour.png
experiments/post_processing.py
experiments/run.py
experiments/simulation_configuration.py
experiments/templates/eth_price_eth_staked_grid_analysis.py
experiments/templates/eth_price_sweep_analysis.py
cadlabs_ethereum_economic_model-0.0.6a0.dist-info/LICENSE
cadlabs_ethereum_economic_model-0.0.6a0.dist-info/WHEEL
cadlabs_ethereum_economic_model-0.0.6a0.dist-info/METADATA
cadlabs_ethereum_economic_model-0.0.6a0.dist-info/RECORD
